blogstrap/__init__.py
blogstrap/blogstrap.py
blogstrap/builder.py
blogstrap/context.py
blogstrap/templates/404.html
blogstrap/templates/404.md
blogstrap/templates/base.html
blogstrap/templates/index.html
blogstrap/templates/index.md
Blogstrap-0.6.0.dist-info/LICENSE
Blogstrap-0.6.0.dist-info/METADATA
Blogstrap-0.6.0.dist-info/WHEEL
Blogstrap-0.6.0.dist-info/entry_points.txt
Blogstrap-0.6.0.dist-info/top_level.txt
Blogstrap-0.6.0.dist-info/RECORD
