Metadata-Version: 2.1
Name: Blogstrap
Version: 0.6.0
Summary: An opinionated blogging platform
Home-page: http://github.com/joehakimrahme/blogstrap
Author: Joe H. Rahme
Author-email: joehakimrahme@gmail.com
License: UNKNOWN
Download-URL: http://github.com/joehakimrahme/blogstrap/tarball/0.6.0
Platform: UNKNOWN
Requires-Dist: Flask
Requires-Dist: mimerender
Requires-Dist: six
